general_tamsat_alert/__init__.py
general_tamsat_alert/ensembles.py
general_tamsat_alert/misc.py
general_tamsat_alert/periodicity.py
general_tamsat_alert/roc_auc.py
general_tamsat_alert/weighting_functions.py
general_tamsat_alert-1.3.4.dist-info/METADATA
general_tamsat_alert-1.3.4.dist-info/WHEEL
general_tamsat_alert-1.3.4.dist-info/top_level.txt
general_tamsat_alert-1.3.4.dist-info/RECORD
