Metadata-Version: 2.4
Name: general_tamsat_alert
Version: 1.3.4
Author-email: John Ellis <12johnellis@gmail.com>
Classifier: Programming Language :: Python :: 3
Requires-Python: >=3.8
Requires-Dist: numpy
Requires-Dist: xarray
Requires-Dist: scipy
Provides-Extra: fastroc
Requires-Dist: fastroc; extra == "fastroc"
